pyang/__init__.py
pyang/__main__.py
pyang/context.py
pyang/error.py
pyang/grammar.py
pyang/hello.py
pyang/plugin.py
pyang/repository.py
pyang/statements.py
pyang/syntax.py
pyang/types.py
pyang/util.py
pyang/xpath.py
pyang/xpath_lexer.py
pyang/xpath_parser.py
pyang/yacc.py
pyang/yang_parser.py
pyang/yin_parser.py
pyang/plugins/__init__.py
pyang/plugins/bbf.py
pyang/plugins/capability.py
pyang/plugins/check_update.py
pyang/plugins/depend.py
pyang/plugins/flatten.py
pyang/plugins/identifiers.py
pyang/plugins/ieee.py
pyang/plugins/ietf.py
pyang/plugins/jsonxsl.py
pyang/plugins/jstree.py
pyang/plugins/jtox.py
pyang/plugins/lint.py
pyang/plugins/mef.py
pyang/plugins/metadata.py
pyang/plugins/name.py
pyang/plugins/omni.py
pyang/plugins/restconf.py
pyang/plugins/sample-xml-skeleton.py
pyang/plugins/sid.py
pyang/plugins/smi.py
pyang/plugins/structure.py
pyang/plugins/threegpp.py
pyang/plugins/tree.py
pyang/plugins/uml.py
pyang/scripts/__init__.py
pyang/scripts/json2xml.py
pyang/scripts/pyang_tool.py
pyang/scripts/yang2html.py
pyang/transforms/__init__.py
pyang/transforms/edit.py
pyang/translators/__init__.py
pyang/translators/dsdl.py
pyang/translators/schemanode.py
pyang/translators/yang.py
pyang/translators/yin.py
pyang-2.7.0.data/data/etc/bash_completion.d/pyang
pyang-2.7.0.data/data/share/man/man1/json2xml.1
pyang-2.7.0.data/data/share/man/man1/pyang.1
pyang-2.7.0.data/data/share/man/man1/yang2dsdl.1
pyang-2.7.0.data/data/share/yang/images/case.png
pyang-2.7.0.data/data/share/yang/images/choice.png
pyang-2.7.0.data/data/share/yang/images/container.png
pyang-2.7.0.data/data/share/yang/images/file.gif
pyang-2.7.0.data/data/share/yang/images/focus.png
pyang-2.7.0.data/data/share/yang/images/folder-closed.gif
pyang-2.7.0.data/data/share/yang/images/folder-open.gif
pyang-2.7.0.data/data/share/yang/images/hammer.png
pyang-2.7.0.data/data/share/yang/images/leaf-list.png
pyang-2.7.0.data/data/share/yang/images/leaf-plus.png
pyang-2.7.0.data/data/share/yang/images/leaf.png
pyang-2.7.0.dist-info/licenses/LICENSE
pyang-2.7.0.dist-info/METADATA
pyang-2.7.0.dist-info/WHEEL
pyang-2.7.0.dist-info/entry_points.txt
pyang-2.7.0.dist-info/top_level.txt
pyang-2.7.0.dist-info/RECORD
